heytelecom/__init__.py
heytelecom/client.py
heytelecom/installer.py
heytelecom/models.py
heytelecom/parsers.py
heytelecom-0.1.1.dist-info/licenses/LICENSE
heytelecom-0.1.1.dist-info/METADATA
heytelecom-0.1.1.dist-info/WHEEL
heytelecom-0.1.1.dist-info/entry_points.txt
heytelecom-0.1.1.dist-info/top_level.txt
heytelecom-0.1.1.dist-info/RECORD
