Metadata-Version: 2.4
Name: heytelecom
Version: 0.1.1
Summary: A Python library for interacting with Hey Telecom accounts
Author-email: CoderMauro <mauro.druwel@gmail.com>
Project-URL: Homepage, https://github.com/maurodruwel/heytelecom
Project-URL: Repository, https://github.com/maurodruwel/heytelecom
Keywords: hey,telecom,hey!,belgium,mobile,internet
Classifier: Development Status :: 3 - Alpha
Classifier: Intended Audience :: Developers
Classifier: License :: OSI Approved :: MIT License
Classifier: Programming Language :: Python :: 3
Classifier: Programming Language :: Python :: 3.8
Classifier: Programming Language :: Python :: 3.9
Classifier: Programming Language :: Python :: 3.10
Classifier: Programming Language :: Python :: 3.11
Classifier: Programming Language :: Python :: 3.12
Classifier: Programming Language :: Python :: 3.13
Classifier: Programming Language :: Python :: 3.14
Requires-Python: >=3.8
License-File: LICENSE
Requires-Dist: playwright
Provides-Extra: dev
Requires-Dist: pytest; extra == "dev"
Requires-Dist: pytest-cov; extra == "dev"
Dynamic: license-file
